LICENSE.txt
README.md
setup.cfg
setup.py
bin/lm-zoo
lm_zoo/__init__.py
lm_zoo/commands.py
lm_zoo/constants.py
lm_zoo/errors.py
lm_zoo/models.py
lm_zoo.egg-info/PKG-INFO
lm_zoo.egg-info/SOURCES.txt
lm_zoo.egg-info/dependency_links.txt
lm_zoo.egg-info/requires.txt
lm_zoo.egg-info/top_level.txt
lm_zoo/backends/__init__.py
lm_zoo/backends/container.py
lm_zoo/backends/docker.py
lm_zoo/backends/python.py
lm_zoo/backends/singularity.py
test/test_commands.py
test/test_lm_zoo.py