Metadata-Version: 2.1
Name: lm-zoo
Version: 1.3
Summary: Command-line interface with state-of-the-art neural network language models
Home-page: https://cpllab.github.io/lm-zoo
Author: Jon Gauthier
Author-email: jon@gauthiers.net
Maintainer: Jon Gauthier
Maintainer-email: jon@gauthiers.net
License: MIT
Keywords: language models,nlp,ai
Platform: UNKNOWN
Requires-Python: >=3.6
